igscrap/__init__.py
igscrap/main.py
igscrap-0.1.0.dist-info/METADATA
igscrap-0.1.0.dist-info/WHEEL
igscrap-0.1.0.dist-info/entry_points.txt
igscrap-0.1.0.dist-info/top_level.txt
igscrap-0.1.0.dist-info/RECORD
