Metadata-Version: 2.1
Name: igscrap
Version: 0.1.0
Summary: A tool to download Instagram posts and send them to Zapier to save in Google Drive
Home-page: https://github.com/eliefrancois/igscrap
Author: EBF Tech
Author-email: ebftech22@gmail.com
Classifier: Programming Language :: Python :: 3
Classifier: License :: OSI Approved :: MIT License
Classifier: Operating System :: OS Independent
Requires-Python: >=3.6
Requires-Dist: instaloader>=4.9.5
Requires-Dist: requests>=2.28.2
